MANIFEST.in
README.md
requirements.txt
setup.py
keras_trans_mask/__init__.py
keras_trans_mask/masks.py
keras_trans_mask.egg-info/PKG-INFO
keras_trans_mask.egg-info/SOURCES.txt
keras_trans_mask.egg-info/dependency_links.txt
keras_trans_mask.egg-info/requires.txt
keras_trans_mask.egg-info/top_level.txt
tests/__init__.py
tests/test_masks.py