Metadata-Version: 2.1
Name: keras-trans-mask
Version: 0.6.0
Summary: Transfer masking in Keras
Home-page: https://github.com/CyberZHG/keras-trans-mask
Author: CyberZHG
Author-email: CyberZHG@users.noreply.github.com
License: MIT
Platform: UNKNOWN
Classifier: Programming Language :: Python :: 3
Classifier: License :: OSI Approved :: MIT License
Classifier: Operating System :: OS Independent
